burau/__init__.py
burau/curve.py
tests/__init__.py
tests/test_curve.py
burau-0.0.4.dist-info/LICENSE
burau-0.0.4.dist-info/METADATA
burau-0.0.4.dist-info/WHEEL
burau-0.0.4.dist-info/top_level.txt
burau-0.0.4.dist-info/RECORD
