Metadata-Version: 2.1
Name: burau
Version: 0.0.4
Summary: Search for non-trivial elements of the kernel of the Burau representation of the four-strand braid group.
Home-page: https://github.com/fuglede/burau
Author: Søren Fuglede Jørgensen
Author-email: pypi@fuglede.dk
Classifier: Programming Language :: Python :: 3
Classifier: License :: OSI Approved :: MIT License
Classifier: Operating System :: OS Independent
Requires-Python: >=3.6
License-File: LICENSE
Requires-Dist: numba
Requires-Dist: numpy
